{"name":"master_weapon7","armature":[{"animation":[{"name":"idle","scale":1,"duration":24,"autoTween":0,"tweenEasing":null,"timeline":[{"offset":0,"name":"weapon7_1","scale":1,"frame":[{"z":0,"transform":{"x":-9.9,"skX":-91.09,"pX":0,"y":-15.5,"skY":-91.09,"pY":0,"scY":1,"scX":-1},"duration":24}]}],"loop":0,"fadeInTime":0},{"name":"attack1","scale":0.4,"duration":26,"autoTween":0,"tweenEasing":null,"timeline":[{"offset":0,"name":"weapon7_1","scale":1,"frame":[{"z":0,"transform":{"x":30.05,"skX":51.95,"pX":0,"y":-34.7,"skY":51.95,"pY":0,"scY":1,"scX":1},"duration":26}]}],"loop":0,"fadeInTime":0},{"name":"attack2","scale":0.4,"duration":25,"autoTween":0,"tweenEasing":null,"timeline":[{"offset":0,"name":"weapon7_1","scale":1,"frame":[{"z":0,"transform":{"x":-20.2,"skX":-65.14,"pX":0,"y":-47.75,"skY":-65.14,"pY":0,"scY":1,"scX":-1},"duration":25}]}],"loop":0,"fadeInTime":0},{"name":"attack3","scale":0.4,"duration":25,"autoTween":0,"tweenEasing":null,"timeline":[{"offset":0,"name":"weapon7_1","scale":1,"frame":[{"z":0,"transform":{"x":28.85,"skX":105.92,"pX":0,"y":-25.05,"skY":105.92,"pY":0,"scY":1,"scX":1},"duration":25}]}],"loop":0,"fadeInTime":0},{"name":"attack4","scale":0.4,"duration":24,"autoTween":0,"tweenEasing":null,"timeline":[{"offset":0,"name":"weapon7_1","scale":1,"frame":[{"z":0,"transform":{"x":-16.8,"skX":-95.06,"pX":0,"y":-15.6,"skY":-95.06,"pY":0,"scY":1,"scX":-1},"duration":24}]}],"loop":0,"fadeInTime":0},{"name":"attack5","scale":0.4,"duration":24,"autoTween":0,"tweenEasing":null,"timeline":[{"offset":0,"name":"weapon7_1","scale":1,"frame":[{"z":0,"transform":{"x":-16,"skX":-36.85,"pX":0,"y":-44.7,"skY":-36.85,"pY":0,"scY":1,"scX":-1},"duration":24}]}],"loop":0,"fadeInTime":0}],"bone":[{"transform":{"x":-9.9,"skX":-91.09,"y":-15.5,"skY":-91.09,"scY":1,"scX":-1},"name":"weapon7_1"}],"skin":[{"name":"default","slot":[{"display":[{"type":"image","name":"weapon7_2","transform":{"x":0,"skX":0,"pX":12.2,"y":0,"skY":0,"pY":53.3,"scY":1,"scX":1}}],"name":"weapon7_1","z":0,"parent":"weapon7_1"}]}],"name":"master_weapon7"}],"version":2.3,"frameRate":24}